<?xml version="1.0" encoding="UTF-8"?>
<openmensa version="2.1" xmlns="http://openmensa.org/open-mensa-v2" xmlns:xsi="http://www.w3.org/2001/XMLSchema-instance" xsi:schemaLocation="http://openmensa.org/open-mensa-v2 http://openmensa.org/open-mensa-v2.xsd">
  <canteen>
    <day date="2025-11-10">
      <category name="Salate">
        <meal>
          <name>Große Salatschale</name>
          <note>Das Gericht  verbessert  die CO₂-Bilanz  leicht .</note>
          <note>Der Wasserverbrauch für dieses Gericht ist mehr als doppelt so hoch wie der Durchschnitt.</note>
          <note>Grüner Ampelpunkt:  Die beste Wahl – je öfter, desto besser.</note>
          <note>Vegan:  Gericht ist aus ausschließlich pflanzlichen Rohstoffen zubereitet.</note>
          <price role="employee">3.90</price>
          <price role="other">4.50</price>
          <price role="student">1.95</price>
        </meal>
        <meal>
          <name>Kleine Salatschale</name>
          <note>Das Gericht  verbessert  die CO₂-Bilanz  wesentlich .</note>
          <note>Der Wasserverbrauch für dieses Gericht ist mehr als doppelt so hoch wie der Durchschnitt.</note>
          <note>Grüner Ampelpunkt:  Die beste Wahl – je öfter, desto besser.</note>
          <note>Vegan:  Gericht ist aus ausschließlich pflanzlichen Rohstoffen zubereitet.</note>
          <price role="employee">1.50</price>
          <price role="other">1.75</price>
          <price role="student">0.75</price>
        </meal>
        <meal>
          <name>Kräuter-Dressing</name>
          <note>Das Gericht  verbessert  die CO₂-Bilanz  wesentlich .</note>
          <note>Der Wasserverbrauch für dieses Gericht liegt unter dem Durchschnitt.</note>
          <note>Roter Ampelpunkt:  Eher selten – am besten mit Grün kombinieren.</note>
          <note>Vegan:  Gericht ist aus ausschließlich pflanzlichen Rohstoffen zubereitet.</note>
        </meal>
        <meal>
          <name>Sauce Vinaigrette</name>
          <note>Das Gericht  verbessert  die CO₂-Bilanz  wesentlich .</note>
          <note>Der Wasserverbrauch für dieses Gericht liegt unter dem Durchschnitt.</note>
          <note>Roter Ampelpunkt:  Eher selten – am besten mit Grün kombinieren.</note>
          <note>Vegan:  Gericht ist aus ausschließlich pflanzlichen Rohstoffen zubereitet.</note>
        </meal>
      </category>
      <category name="Essen">
        <meal>
          <name>6 Weizeneiweißbällchen an Tomaten-Zucchini-Sauce</name>
          <note>Gelber Ampelpunkt:  Eine gute Wahl – immer mal wieder.</note>
          <note>Vegan:  Gericht ist aus ausschließlich pflanzlichen Rohstoffen zubereitet.</note>
          <price role="employee">3.50</price>
          <price role="other">4.05</price>
          <price role="student">1.75</price>
        </meal>
        <meal>
          <name>Edamame Bratling an Tahin-Dip mit frischen Kräutern</name>
          <note>Das Gericht  verbessert  die CO₂-Bilanz  wesentlich .</note>
          <note>Der Wasserverbrauch für dieses Gericht liegt unter dem Durchschnitt.</note>
          <note>Grüner Ampelpunkt:  Die beste Wahl – je öfter, desto besser.</note>
          <note>Vegan:  Gericht ist aus ausschließlich pflanzlichen Rohstoffen zubereitet.</note>
          <price role="employee">3.50</price>
          <price role="other">4.05</price>
          <price role="student">1.75</price>
        </meal>
        <meal>
          <name>Paella Spanische Gemüse-Reis-Pfanne</name>
          <note>Gelber Ampelpunkt:  Eine gute Wahl – immer mal wieder.</note>
          <note>Vegan:  Gericht ist aus ausschließlich pflanzlichen Rohstoffen zubereitet.</note>
          <price role="employee">3.50</price>
          <price role="other">4.05</price>
          <price role="student">1.75</price>
        </meal>
      </category>
      <category name="Beilagen">
        <meal>
          <name>Fingermöhren</name>
          <note>Grüner Ampelpunkt:  Die beste Wahl – je öfter, desto besser.</note>
          <note>Vegan:  Gericht ist aus ausschließlich pflanzlichen Rohstoffen zubereitet.</note>
          <price role="employee">1.70</price>
          <price role="other">1.95</price>
          <price role="student">0.85</price>
        </meal>
        <meal>
          <name>Kartoffeln</name>
          <note>Das Gericht  verbessert  die CO₂-Bilanz  wesentlich .</note>
          <note>Der Wasserverbrauch für dieses Gericht liegt unter dem Durchschnitt.</note>
          <note>Grüner Ampelpunkt:  Die beste Wahl – je öfter, desto besser.</note>
          <note>Vegan:  Gericht ist aus ausschließlich pflanzlichen Rohstoffen zubereitet.</note>
          <price role="employee">1.70</price>
          <price role="other">1.95</price>
          <price role="student">0.85</price>
        </meal>
        <meal>
          <name>Parboiledreis</name>
          <note>Gelber Ampelpunkt:  Eine gute Wahl – immer mal wieder.</note>
          <note>Vegan:  Gericht ist aus ausschließlich pflanzlichen Rohstoffen zubereitet.</note>
          <price role="employee">1.50</price>
          <price role="other">1.75</price>
          <price role="student">0.75</price>
        </meal>
        <meal>
          <name>Sauce &amp; Dip Extra</name>
          <note>Vegan:  Gericht ist aus ausschließlich pflanzlichen Rohstoffen zubereitet.</note>
          <price role="employee">0.60</price>
          <price role="other">0.70</price>
          <price role="student">0.30</price>
        </meal>
      </category>
      <category name="Desserts">
        <meal>
          <name>Quark mit Früchten</name>
          <note>Roter Ampelpunkt:  Eher selten – am besten mit Grün kombinieren.</note>
          <note>Vegetarisch:  Gerichte werden ohne Fisch- und Fleischzutaten zubereitet.</note>
          <price role="employee">1.50</price>
          <price role="other">1.75</price>
          <price role="student">0.75</price>
        </meal>
        <meal>
          <name>Veganer Joghurt mit Früchten</name>
          <note>Grüner Ampelpunkt:  Die beste Wahl – je öfter, desto besser.</note>
          <note>Vegan:  Gericht ist aus ausschließlich pflanzlichen Rohstoffen zubereitet.</note>
          <price role="employee">1.50</price>
          <price role="other">1.75</price>
          <price role="student">0.75</price>
        </meal>
        <meal>
          <name>Joghurt mit Früchten</name>
          <note>Grüner Ampelpunkt:  Die beste Wahl – je öfter, desto besser.</note>
          <note>Vegetarisch:  Gerichte werden ohne Fisch- und Fleischzutaten zubereitet.</note>
          <price role="employee">1.50</price>
          <price role="other">1.75</price>
          <price role="student">0.75</price>
        </meal>
        <meal>
          <name>Veganer Pudding</name>
          <note>Gelber Ampelpunkt:  Eine gute Wahl – immer mal wieder.</note>
          <note>Vegan:  Gericht ist aus ausschließlich pflanzlichen Rohstoffen zubereitet.</note>
          <price role="employee">1.50</price>
          <price role="other">1.75</price>
          <price role="student">0.75</price>
        </meal>
      </category>
    </day>
    <day date="2025-11-11">
      <category name="Salate">
        <meal>
          <name>Große Salatschale</name>
          <note>Das Gericht  verbessert  die CO₂-Bilanz  leicht .</note>
          <note>Der Wasserverbrauch für dieses Gericht ist mehr als doppelt so hoch wie der Durchschnitt.</note>
          <note>Grüner Ampelpunkt:  Die beste Wahl – je öfter, desto besser.</note>
          <note>Vegan:  Gericht ist aus ausschließlich pflanzlichen Rohstoffen zubereitet.</note>
          <price role="employee">3.90</price>
          <price role="other">4.50</price>
          <price role="student">1.95</price>
        </meal>
        <meal>
          <name>Kleine Salatschale</name>
          <note>Das Gericht  verbessert  die CO₂-Bilanz  wesentlich .</note>
          <note>Der Wasserverbrauch für dieses Gericht ist mehr als doppelt so hoch wie der Durchschnitt.</note>
          <note>Grüner Ampelpunkt:  Die beste Wahl – je öfter, desto besser.</note>
          <note>Vegan:  Gericht ist aus ausschließlich pflanzlichen Rohstoffen zubereitet.</note>
          <price role="employee">1.50</price>
          <price role="other">1.75</price>
          <price role="student">0.75</price>
        </meal>
        <meal>
          <name>Kräuter-Dressing</name>
          <note>Das Gericht  verbessert  die CO₂-Bilanz  wesentlich .</note>
          <note>Der Wasserverbrauch für dieses Gericht liegt unter dem Durchschnitt.</note>
          <note>Roter Ampelpunkt:  Eher selten – am besten mit Grün kombinieren.</note>
          <note>Vegan:  Gericht ist aus ausschließlich pflanzlichen Rohstoffen zubereitet.</note>
        </meal>
        <meal>
          <name>Sauce Vinaigrette</name>
          <note>Das Gericht  verbessert  die CO₂-Bilanz  wesentlich .</note>
          <note>Der Wasserverbrauch für dieses Gericht liegt unter dem Durchschnitt.</note>
          <note>Roter Ampelpunkt:  Eher selten – am besten mit Grün kombinieren.</note>
          <note>Vegan:  Gericht ist aus ausschließlich pflanzlichen Rohstoffen zubereitet.</note>
        </meal>
      </category>
      <category name="Aktionen">
        <meal>
          <name>Pasta mit Tomatensauce und Tofu</name>
          <note>Grüner Ampelpunkt:  Die beste Wahl – je öfter, desto besser.</note>
          <note>Nachhaltige Landwirtschaft:  Die Lebensmittel dieses Gerichts stammen aus nachhaltiger Erzeugung.</note>
          <note>Vegan:  Gericht ist aus ausschließlich pflanzlichen Rohstoffen zubereitet.</note>
          <price role="employee">3.25</price>
          <price role="other">3.55</price>
          <price role="student">2.95</price>
        </meal>
      </category>
      <category name="Essen">
        <meal>
          <name>Kohlroulade mit Gemüsefüllung an Kräutersauce</name>
          <note>Das Gericht  verbessert  die CO₂-Bilanz  wesentlich .</note>
          <note>Der Wasserverbrauch für dieses Gericht liegt unter dem Durchschnitt.</note>
          <note>Grüner Ampelpunkt:  Die beste Wahl – je öfter, desto besser.</note>
          <note>Vegan:  Gericht ist aus ausschließlich pflanzlichen Rohstoffen zubereitet.</note>
          <price role="employee">3.50</price>
          <price role="other">4.05</price>
          <price role="student">1.75</price>
        </meal>
        <meal>
          <name>Mexikanischer Bohneneintopf mit Sojahack und Chili</name>
          <note>Grüner Ampelpunkt:  Die beste Wahl – je öfter, desto besser.</note>
          <note>Vegan:  Gericht ist aus ausschließlich pflanzlichen Rohstoffen zubereitet.</note>
          <price role="employee">3.50</price>
          <price role="other">4.05</price>
          <price role="student">1.75</price>
        </meal>
      </category>
      <category name="Beilagen">
        <meal>
          <name>Rosenkohl</name>
          <note>Das Gericht  verbessert  die CO₂-Bilanz  wesentlich .</note>
          <note>Der Wasserverbrauch für dieses Gericht liegt unter dem Durchschnitt.</note>
          <note>Grüner Ampelpunkt:  Die beste Wahl – je öfter, desto besser.</note>
          <note>Vegan:  Gericht ist aus ausschließlich pflanzlichen Rohstoffen zubereitet.</note>
          <price role="employee">1.70</price>
          <price role="other">1.95</price>
          <price role="student">0.85</price>
        </meal>
        <meal>
          <name>Petersilienkartoffeln</name>
          <note>Das Gericht  verbessert  die CO₂-Bilanz  wesentlich .</note>
          <note>Der Wasserverbrauch für dieses Gericht liegt unter dem Durchschnitt.</note>
          <note>Grüner Ampelpunkt:  Die beste Wahl – je öfter, desto besser.</note>
          <note>Vegan:  Gericht ist aus ausschließlich pflanzlichen Rohstoffen zubereitet.</note>
          <price role="employee">1.70</price>
          <price role="other">1.95</price>
          <price role="student">0.85</price>
        </meal>
        <meal>
          <name>Curryreis</name>
          <note>Das Gericht  verbessert  die CO₂-Bilanz  wesentlich .</note>
          <note>Der Wasserverbrauch für dieses Gericht ist doppelt so hoch wie der Durchschnitt.</note>
          <note>Gelber Ampelpunkt:  Eine gute Wahl – immer mal wieder.</note>
          <note>Vegan:  Gericht ist aus ausschließlich pflanzlichen Rohstoffen zubereitet.</note>
          <price role="employee">1.50</price>
          <price role="other">1.75</price>
          <price role="student">0.75</price>
        </meal>
        <meal>
          <name>Sauce &amp; Dip Extra</name>
          <note>Vegan:  Gericht ist aus ausschließlich pflanzlichen Rohstoffen zubereitet.</note>
          <price role="employee">0.60</price>
          <price role="other">0.70</price>
          <price role="student">0.30</price>
        </meal>
      </category>
      <category name="Desserts">
        <meal>
          <name>Veganer Joghurt mit Früchten</name>
          <note>Grüner Ampelpunkt:  Die beste Wahl – je öfter, desto besser.</note>
          <note>Vegan:  Gericht ist aus ausschließlich pflanzlichen Rohstoffen zubereitet.</note>
          <price role="employee">1.50</price>
          <price role="other">1.75</price>
          <price role="student">0.75</price>
        </meal>
        <meal>
          <name>Joghurt mit Früchten</name>
          <note>Grüner Ampelpunkt:  Die beste Wahl – je öfter, desto besser.</note>
          <note>Vegetarisch:  Gerichte werden ohne Fisch- und Fleischzutaten zubereitet.</note>
          <price role="employee">1.50</price>
          <price role="other">1.75</price>
          <price role="student">0.75</price>
        </meal>
        <meal>
          <name>Quark mit Früchten</name>
          <note>Roter Ampelpunkt:  Eher selten – am besten mit Grün kombinieren.</note>
          <note>Vegetarisch:  Gerichte werden ohne Fisch- und Fleischzutaten zubereitet.</note>
          <price role="employee">1.50</price>
          <price role="other">1.75</price>
          <price role="student">0.75</price>
        </meal>
        <meal>
          <name>Veganer Pudding</name>
          <note>Gelber Ampelpunkt:  Eine gute Wahl – immer mal wieder.</note>
          <note>Vegan:  Gericht ist aus ausschließlich pflanzlichen Rohstoffen zubereitet.</note>
          <price role="employee">1.50</price>
          <price role="other">1.75</price>
          <price role="student">0.75</price>
        </meal>
      </category>
    </day>
    <day date="2025-11-12">
      <category name="Salate">
        <meal>
          <name>Große Salatschale</name>
          <note>Das Gericht  verbessert  die CO₂-Bilanz  leicht .</note>
          <note>Der Wasserverbrauch für dieses Gericht ist mehr als doppelt so hoch wie der Durchschnitt.</note>
          <note>Grüner Ampelpunkt:  Die beste Wahl – je öfter, desto besser.</note>
          <note>Vegan:  Gericht ist aus ausschließlich pflanzlichen Rohstoffen zubereitet.</note>
          <price role="employee">3.90</price>
          <price role="other">4.50</price>
          <price role="student">1.95</price>
        </meal>
        <meal>
          <name>Kleine Salatschale</name>
          <note>Das Gericht  verbessert  die CO₂-Bilanz  wesentlich .</note>
          <note>Der Wasserverbrauch für dieses Gericht ist mehr als doppelt so hoch wie der Durchschnitt.</note>
          <note>Grüner Ampelpunkt:  Die beste Wahl – je öfter, desto besser.</note>
          <note>Vegan:  Gericht ist aus ausschließlich pflanzlichen Rohstoffen zubereitet.</note>
          <price role="employee">1.50</price>
          <price role="other">1.75</price>
          <price role="student">0.75</price>
        </meal>
        <meal>
          <name>Kräuter-Dressing</name>
          <note>Das Gericht  verbessert  die CO₂-Bilanz  wesentlich .</note>
          <note>Der Wasserverbrauch für dieses Gericht liegt unter dem Durchschnitt.</note>
          <note>Roter Ampelpunkt:  Eher selten – am besten mit Grün kombinieren.</note>
          <note>Vegan:  Gericht ist aus ausschließlich pflanzlichen Rohstoffen zubereitet.</note>
        </meal>
        <meal>
          <name>Sauce Vinaigrette</name>
          <note>Das Gericht  verbessert  die CO₂-Bilanz  wesentlich .</note>
          <note>Der Wasserverbrauch für dieses Gericht liegt unter dem Durchschnitt.</note>
          <note>Roter Ampelpunkt:  Eher selten – am besten mit Grün kombinieren.</note>
          <note>Vegan:  Gericht ist aus ausschließlich pflanzlichen Rohstoffen zubereitet.</note>
        </meal>
      </category>
      <category name="Essen">
        <meal>
          <name>Frikadelle aus Weizeneiweiß an Kräuterjus</name>
          <note>Roter Ampelpunkt:  Eher selten – am besten mit Grün kombinieren.</note>
          <note>Vegan:  Gericht ist aus ausschließlich pflanzlichen Rohstoffen zubereitet.</note>
          <price role="employee">3.50</price>
          <price role="other">4.05</price>
          <price role="student">1.75</price>
        </meal>
        <meal>
          <name>Kartoffel-Gemüse-Auflauf mit Käse</name>
          <note>Das Gericht  verbessert  die CO₂-Bilanz  leicht .</note>
          <note>Der Wasserverbrauch für dieses Gericht liegt unter dem Durchschnitt.</note>
          <note>Grüner Ampelpunkt:  Die beste Wahl – je öfter, desto besser.</note>
          <note>Vegetarisch:  Gerichte werden ohne Fisch- und Fleischzutaten zubereitet.</note>
          <price role="employee">3.50</price>
          <price role="other">4.05</price>
          <price role="student">1.75</price>
        </meal>
        <meal>
          <name>Germknödel mit Pflaumenmusfüllung, Mohnzucker und Vanillesauce</name>
          <note>Gelber Ampelpunkt:  Eine gute Wahl – immer mal wieder.</note>
          <note>Vegetarisch:  Gerichte werden ohne Fisch- und Fleischzutaten zubereitet.</note>
          <price role="employee">3.50</price>
          <price role="other">4.05</price>
          <price role="student">1.75</price>
        </meal>
      </category>
      <category name="Beilagen">
        <meal>
          <name>Blumenkohl mit Sesam</name>
          <note>Das Gericht  verbessert  die CO₂-Bilanz  leicht .</note>
          <note>Der Wasserverbrauch für dieses Gericht liegt unter dem Durchschnitt.</note>
          <note>Grüner Ampelpunkt:  Die beste Wahl – je öfter, desto besser.</note>
          <note>Vegan:  Gericht ist aus ausschließlich pflanzlichen Rohstoffen zubereitet.</note>
          <price role="employee">1.70</price>
          <price role="other">1.95</price>
          <price role="student">0.85</price>
        </meal>
        <meal>
          <name>Kartoffeln</name>
          <note>Das Gericht  verbessert  die CO₂-Bilanz  wesentlich .</note>
          <note>Der Wasserverbrauch für dieses Gericht liegt unter dem Durchschnitt.</note>
          <note>Grüner Ampelpunkt:  Die beste Wahl – je öfter, desto besser.</note>
          <note>Vegan:  Gericht ist aus ausschließlich pflanzlichen Rohstoffen zubereitet.</note>
          <price role="employee">1.70</price>
          <price role="other">1.95</price>
          <price role="student">0.85</price>
        </meal>
        <meal>
          <name>Mandelreis</name>
          <note>Das Gericht  verbessert  die CO₂-Bilanz  wesentlich .</note>
          <note>Der Wasserverbrauch für dieses Gericht ist mehr als doppelt so hoch wie der Durchschnitt.</note>
          <note>Gelber Ampelpunkt:  Eine gute Wahl – immer mal wieder.</note>
          <note>Vegan:  Gericht ist aus ausschließlich pflanzlichen Rohstoffen zubereitet.</note>
          <price role="employee">1.50</price>
          <price role="other">1.75</price>
          <price role="student">0.75</price>
        </meal>
        <meal>
          <name>Sauce &amp; Dip Extra</name>
          <note>Vegan:  Gericht ist aus ausschließlich pflanzlichen Rohstoffen zubereitet.</note>
          <price role="employee">0.60</price>
          <price role="other">0.70</price>
          <price role="student">0.30</price>
        </meal>
      </category>
      <category name="Desserts">
        <meal>
          <name>Quark mit Früchten</name>
          <note>Roter Ampelpunkt:  Eher selten – am besten mit Grün kombinieren.</note>
          <note>Vegetarisch:  Gerichte werden ohne Fisch- und Fleischzutaten zubereitet.</note>
          <price role="employee">1.50</price>
          <price role="other">1.75</price>
          <price role="student">0.75</price>
        </meal>
        <meal>
          <name>Veganer Joghurt mit Früchten</name>
          <note>Grüner Ampelpunkt:  Die beste Wahl – je öfter, desto besser.</note>
          <note>Vegan:  Gericht ist aus ausschließlich pflanzlichen Rohstoffen zubereitet.</note>
          <price role="employee">1.50</price>
          <price role="other">1.75</price>
          <price role="student">0.75</price>
        </meal>
        <meal>
          <name>Joghurt mit Früchten</name>
          <note>Grüner Ampelpunkt:  Die beste Wahl – je öfter, desto besser.</note>
          <note>Vegetarisch:  Gerichte werden ohne Fisch- und Fleischzutaten zubereitet.</note>
          <price role="employee">1.50</price>
          <price role="other">1.75</price>
          <price role="student">0.75</price>
        </meal>
        <meal>
          <name>Veganer Pudding</name>
          <note>Gelber Ampelpunkt:  Eine gute Wahl – immer mal wieder.</note>
          <note>Vegan:  Gericht ist aus ausschließlich pflanzlichen Rohstoffen zubereitet.</note>
          <price role="employee">1.50</price>
          <price role="other">1.75</price>
          <price role="student">0.75</price>
        </meal>
      </category>
    </day>
    <day date="2025-11-13">
      <category name="Salate">
        <meal>
          <name>Große Salatschale</name>
          <note>Das Gericht  verbessert  die CO₂-Bilanz  leicht .</note>
          <note>Der Wasserverbrauch für dieses Gericht ist mehr als doppelt so hoch wie der Durchschnitt.</note>
          <note>Grüner Ampelpunkt:  Die beste Wahl – je öfter, desto besser.</note>
          <note>Vegan:  Gericht ist aus ausschließlich pflanzlichen Rohstoffen zubereitet.</note>
          <price role="employee">3.90</price>
          <price role="other">4.50</price>
          <price role="student">1.95</price>
        </meal>
        <meal>
          <name>Kleine Salatschale</name>
          <note>Das Gericht  verbessert  die CO₂-Bilanz  wesentlich .</note>
          <note>Der Wasserverbrauch für dieses Gericht ist mehr als doppelt so hoch wie der Durchschnitt.</note>
          <note>Grüner Ampelpunkt:  Die beste Wahl – je öfter, desto besser.</note>
          <note>Vegan:  Gericht ist aus ausschließlich pflanzlichen Rohstoffen zubereitet.</note>
          <price role="employee">1.50</price>
          <price role="other">1.75</price>
          <price role="student">0.75</price>
        </meal>
        <meal>
          <name>Kräuter-Dressing</name>
          <note>Das Gericht  verbessert  die CO₂-Bilanz  wesentlich .</note>
          <note>Der Wasserverbrauch für dieses Gericht liegt unter dem Durchschnitt.</note>
          <note>Roter Ampelpunkt:  Eher selten – am besten mit Grün kombinieren.</note>
          <note>Vegan:  Gericht ist aus ausschließlich pflanzlichen Rohstoffen zubereitet.</note>
        </meal>
        <meal>
          <name>Sauce Vinaigrette</name>
          <note>Das Gericht  verbessert  die CO₂-Bilanz  wesentlich .</note>
          <note>Der Wasserverbrauch für dieses Gericht liegt unter dem Durchschnitt.</note>
          <note>Roter Ampelpunkt:  Eher selten – am besten mit Grün kombinieren.</note>
          <note>Vegan:  Gericht ist aus ausschließlich pflanzlichen Rohstoffen zubereitet.</note>
        </meal>
      </category>
      <category name="Aktionen">
        <meal>
          <name>Pasta mit Sojabolognese</name>
          <note>Gelber Ampelpunkt:  Eine gute Wahl – immer mal wieder.</note>
          <note>Vegan:  Gericht ist aus ausschließlich pflanzlichen Rohstoffen zubereitet.</note>
          <price role="employee">3.25</price>
          <price role="other">3.55</price>
          <price role="student">2.95</price>
        </meal>
      </category>
      <category name="Essen">
        <meal>
          <name>Zwei Sesam-Karotten-Sticks an Curry-Mango-Sauce</name>
          <note>Das Gericht  verbessert  die CO₂-Bilanz  wesentlich .</note>
          <note>Der Wasserverbrauch für dieses Gericht liegt unter dem Durchschnitt.</note>
          <note>Roter Ampelpunkt:  Eher selten – am besten mit Grün kombinieren.</note>
          <note>Vegan:  Gericht ist aus ausschließlich pflanzlichen Rohstoffen zubereitet.</note>
          <price role="employee">4.90</price>
          <price role="other">5.65</price>
          <price role="student">2.45</price>
        </meal>
        <meal>
          <name>Berliner Kartoffelsuppe mit Möhren und Knollensellerie</name>
          <note>Das Gericht  verbessert  die CO₂-Bilanz  wesentlich .</note>
          <note>Der Wasserverbrauch für dieses Gericht liegt unter dem Durchschnitt.</note>
          <note>Grüner Ampelpunkt:  Die beste Wahl – je öfter, desto besser.</note>
          <note>Vegan:  Gericht ist aus ausschließlich pflanzlichen Rohstoffen zubereitet.</note>
          <price role="employee">3.50</price>
          <price role="other">4.05</price>
          <price role="student">1.75</price>
        </meal>
      </category>
      <category name="Beilagen">
        <meal>
          <name>Sellerie</name>
          <note>Das Gericht  verbessert  die CO₂-Bilanz  leicht .</note>
          <note>Der Wasserverbrauch für dieses Gericht liegt unter dem Durchschnitt.</note>
          <note>Grüner Ampelpunkt:  Die beste Wahl – je öfter, desto besser.</note>
          <note>Vegan:  Gericht ist aus ausschließlich pflanzlichen Rohstoffen zubereitet.</note>
          <price role="employee">1.70</price>
          <price role="other">1.95</price>
          <price role="student">0.85</price>
        </meal>
        <meal>
          <name>Kartoffeln</name>
          <note>Das Gericht  verbessert  die CO₂-Bilanz  wesentlich .</note>
          <note>Der Wasserverbrauch für dieses Gericht liegt unter dem Durchschnitt.</note>
          <note>Grüner Ampelpunkt:  Die beste Wahl – je öfter, desto besser.</note>
          <note>Vegan:  Gericht ist aus ausschließlich pflanzlichen Rohstoffen zubereitet.</note>
          <price role="employee">1.70</price>
          <price role="other">1.95</price>
          <price role="student">0.85</price>
        </meal>
        <meal>
          <name>Parboiledreis</name>
          <note>Das Gericht  verbessert  die CO₂-Bilanz  wesentlich .</note>
          <note>Der Wasserverbrauch für dieses Gericht ist doppelt so hoch wie der Durchschnitt.</note>
          <note>Gelber Ampelpunkt:  Eine gute Wahl – immer mal wieder.</note>
          <note>Vegan:  Gericht ist aus ausschließlich pflanzlichen Rohstoffen zubereitet.</note>
          <price role="employee">1.50</price>
          <price role="other">1.75</price>
          <price role="student">0.75</price>
        </meal>
        <meal>
          <name>Sauce &amp; Dip Extra</name>
          <note>Vegan:  Gericht ist aus ausschließlich pflanzlichen Rohstoffen zubereitet.</note>
          <price role="employee">0.60</price>
          <price role="other">0.70</price>
          <price role="student">0.30</price>
        </meal>
      </category>
      <category name="Desserts">
        <meal>
          <name>Quark mit Früchten</name>
          <note>Roter Ampelpunkt:  Eher selten – am besten mit Grün kombinieren.</note>
          <note>Vegetarisch:  Gerichte werden ohne Fisch- und Fleischzutaten zubereitet.</note>
          <price role="employee">1.50</price>
          <price role="other">1.75</price>
          <price role="student">0.75</price>
        </meal>
        <meal>
          <name>Joghurt mit Früchten</name>
          <note>Grüner Ampelpunkt:  Die beste Wahl – je öfter, desto besser.</note>
          <note>Vegetarisch:  Gerichte werden ohne Fisch- und Fleischzutaten zubereitet.</note>
          <price role="employee">1.50</price>
          <price role="other">1.75</price>
          <price role="student">0.75</price>
        </meal>
        <meal>
          <name>Veganer Joghurt mit Früchten</name>
          <note>Grüner Ampelpunkt:  Die beste Wahl – je öfter, desto besser.</note>
          <note>Vegan:  Gericht ist aus ausschließlich pflanzlichen Rohstoffen zubereitet.</note>
          <price role="employee">1.50</price>
          <price role="other">1.75</price>
          <price role="student">0.75</price>
        </meal>
        <meal>
          <name>Veganer Pudding</name>
          <note>Gelber Ampelpunkt:  Eine gute Wahl – immer mal wieder.</note>
          <note>Vegan:  Gericht ist aus ausschließlich pflanzlichen Rohstoffen zubereitet.</note>
          <price role="employee">1.50</price>
          <price role="other">1.75</price>
          <price role="student">0.75</price>
        </meal>
      </category>
    </day>
    <day date="2025-11-14">
      <category name="Salate">
        <meal>
          <name>Große Salatschale</name>
          <note>Das Gericht  verbessert  die CO₂-Bilanz  leicht .</note>
          <note>Der Wasserverbrauch für dieses Gericht ist mehr als doppelt so hoch wie der Durchschnitt.</note>
          <note>Grüner Ampelpunkt:  Die beste Wahl – je öfter, desto besser.</note>
          <note>Vegan:  Gericht ist aus ausschließlich pflanzlichen Rohstoffen zubereitet.</note>
          <price role="employee">3.90</price>
          <price role="other">4.50</price>
          <price role="student">1.95</price>
        </meal>
        <meal>
          <name>Kleine Salatschale</name>
          <note>Das Gericht  verbessert  die CO₂-Bilanz  wesentlich .</note>
          <note>Der Wasserverbrauch für dieses Gericht ist mehr als doppelt so hoch wie der Durchschnitt.</note>
          <note>Grüner Ampelpunkt:  Die beste Wahl – je öfter, desto besser.</note>
          <note>Vegan:  Gericht ist aus ausschließlich pflanzlichen Rohstoffen zubereitet.</note>
          <price role="employee">1.50</price>
          <price role="other">1.75</price>
          <price role="student">0.75</price>
        </meal>
        <meal>
          <name>Kräuter-Dressing</name>
          <note>Das Gericht  verbessert  die CO₂-Bilanz  wesentlich .</note>
          <note>Der Wasserverbrauch für dieses Gericht liegt unter dem Durchschnitt.</note>
          <note>Roter Ampelpunkt:  Eher selten – am besten mit Grün kombinieren.</note>
          <note>Vegan:  Gericht ist aus ausschließlich pflanzlichen Rohstoffen zubereitet.</note>
        </meal>
        <meal>
          <name>Sauce Vinaigrette</name>
          <note>Das Gericht  verbessert  die CO₂-Bilanz  wesentlich .</note>
          <note>Der Wasserverbrauch für dieses Gericht liegt unter dem Durchschnitt.</note>
          <note>Roter Ampelpunkt:  Eher selten – am besten mit Grün kombinieren.</note>
          <note>Vegan:  Gericht ist aus ausschließlich pflanzlichen Rohstoffen zubereitet.</note>
        </meal>
      </category>
      <category name="Essen">
        <meal>
          <name>Gebackenes Seelachsfilet in Knusperpanade an Remouladensauce</name>
          <note>Das Gericht  verbessert  die CO₂-Bilanz  leicht .</note>
          <note>Der Wasserverbrauch für dieses Gericht liegt unter dem Durchschnitt.</note>
          <note>Gelber Ampelpunkt:  Eine gute Wahl – immer mal wieder.</note>
          <note>Nachhaltige Fischerei:  Es wird auf eine bestandsschonende Fischerei und nachhaltige Fangmethoden geachtet.</note>
          <price role="employee">4.30</price>
          <price role="other">4.95</price>
          <price role="student">2.15</price>
        </meal>
        <meal>
          <name>Vegane Frühlingsrolle an bunter Sojasauce</name>
          <note>Gelber Ampelpunkt:  Eine gute Wahl – immer mal wieder.</note>
          <note>Vegan:  Gericht ist aus ausschließlich pflanzlichen Rohstoffen zubereitet.</note>
          <price role="employee">2.70</price>
          <price role="other">3.10</price>
          <price role="student">1.35</price>
        </meal>
      </category>
      <category name="Beilagen">
        <meal>
          <name>Blattspinat</name>
          <note>Das Gericht  verbessert  die CO₂-Bilanz  wesentlich .</note>
          <note>Der Wasserverbrauch für dieses Gericht liegt unter dem Durchschnitt.</note>
          <note>Grüner Ampelpunkt:  Die beste Wahl – je öfter, desto besser.</note>
          <note>Vegan:  Gericht ist aus ausschließlich pflanzlichen Rohstoffen zubereitet.</note>
          <price role="employee">1.70</price>
          <price role="other">1.95</price>
          <price role="student">0.85</price>
        </meal>
        <meal>
          <name>Kartoffeln</name>
          <note>Das Gericht  verbessert  die CO₂-Bilanz  wesentlich .</note>
          <note>Der Wasserverbrauch für dieses Gericht liegt unter dem Durchschnitt.</note>
          <note>Grüner Ampelpunkt:  Die beste Wahl – je öfter, desto besser.</note>
          <note>Vegan:  Gericht ist aus ausschließlich pflanzlichen Rohstoffen zubereitet.</note>
          <price role="employee">1.70</price>
          <price role="other">1.95</price>
          <price role="student">0.85</price>
        </meal>
        <meal>
          <name>Parboiledreis</name>
          <note>Das Gericht  verbessert  die CO₂-Bilanz  wesentlich .</note>
          <note>Der Wasserverbrauch für dieses Gericht ist doppelt so hoch wie der Durchschnitt.</note>
          <note>Gelber Ampelpunkt:  Eine gute Wahl – immer mal wieder.</note>
          <note>Vegan:  Gericht ist aus ausschließlich pflanzlichen Rohstoffen zubereitet.</note>
          <price role="employee">1.50</price>
          <price role="other">1.75</price>
          <price role="student">0.75</price>
        </meal>
        <meal>
          <name>Sauce &amp; Dip Extra</name>
          <note>Vegan:  Gericht ist aus ausschließlich pflanzlichen Rohstoffen zubereitet.</note>
          <price role="employee">0.60</price>
          <price role="other">0.70</price>
          <price role="student">0.30</price>
        </meal>
      </category>
      <category name="Desserts">
        <meal>
          <name>Quark mit Früchten</name>
          <note>Roter Ampelpunkt:  Eher selten – am besten mit Grün kombinieren.</note>
          <note>Vegetarisch:  Gerichte werden ohne Fisch- und Fleischzutaten zubereitet.</note>
          <price role="employee">1.50</price>
          <price role="other">1.75</price>
          <price role="student">0.75</price>
        </meal>
        <meal>
          <name>Joghurt mit Früchten</name>
          <note>Grüner Ampelpunkt:  Die beste Wahl – je öfter, desto besser.</note>
          <note>Vegetarisch:  Gerichte werden ohne Fisch- und Fleischzutaten zubereitet.</note>
          <price role="employee">1.50</price>
          <price role="other">1.75</price>
          <price role="student">0.75</price>
        </meal>
        <meal>
          <name>Veganer Joghurt mit Früchten</name>
          <note>Grüner Ampelpunkt:  Die beste Wahl – je öfter, desto besser.</note>
          <note>Vegan:  Gericht ist aus ausschließlich pflanzlichen Rohstoffen zubereitet.</note>
          <price role="employee">1.50</price>
          <price role="other">1.75</price>
          <price role="student">0.75</price>
        </meal>
        <meal>
          <name>Veganer Pudding</name>
          <note>Gelber Ampelpunkt:  Eine gute Wahl – immer mal wieder.</note>
          <note>Vegan:  Gericht ist aus ausschließlich pflanzlichen Rohstoffen zubereitet.</note>
          <price role="employee">1.50</price>
          <price role="other">1.75</price>
          <price role="student">0.75</price>
        </meal>
      </category>
    </day>
    <day date="2025-11-15">
      <closed/>
    </day>
    <day date="2025-11-16">
      <closed/>
    </day>
  </canteen>
</openmensa>
